sinaraml_cli/__init__.py
sinaraml_cli/_version.py
sinaraml_cli/sinaraml.py
sinaraml_cli-2023.11.17.dist-info/METADATA
sinaraml_cli-2023.11.17.dist-info/WHEEL
sinaraml_cli-2023.11.17.dist-info/entry_points.txt
sinaraml_cli-2023.11.17.dist-info/licenses/LICENSE
sinaraml_cli-2023.11.17.dist-info/RECORD
