Metadata-Version: 2.1
Name: sinaraml_cli
Version: 2023.11.17
Summary: Sinara CLI
Project-URL: Homepage, https://github.com/4-DS/sinaraml_cli
Author-email: sinaraml <sinaraml.official@gmail.com>
License:                                  Apache License
License-File: LICENSE
Keywords: cli,sinaraml
Classifier: License :: OSI Approved :: Apache Software License
Classifier: Operating System :: OS Independent
Classifier: Programming Language :: Python :: 3.6
Classifier: Programming Language :: Python :: 3.7
Classifier: Programming Language :: Python :: 3.8
Classifier: Programming Language :: Python :: Implementation :: CPython
Classifier: Topic :: Scientific/Engineering :: Artificial Intelligence
Requires-Python: >=3.6
Requires-Dist: importlib-metadata; python_version >= '3.6'
